springlabs_cc_ricardo/__init__.py
springlabs_cc_ricardo/main.py
springlabs_cc_ricardo/utils.py
springlabs_cc_ricardo/scripts/__init__.py
springlabs_cc_ricardo/scripts/springlabs_cc_ricardo.py
springlabs_cc_ricardo-0.1.1.dist-info/LICENSE
springlabs_cc_ricardo-0.1.1.dist-info/METADATA
springlabs_cc_ricardo-0.1.1.dist-info/WHEEL
springlabs_cc_ricardo-0.1.1.dist-info/entry_points.txt
springlabs_cc_ricardo-0.1.1.dist-info/top_level.txt
springlabs_cc_ricardo-0.1.1.dist-info/RECORD
