Metadata-Version: 2.1
Name: springlabs-cc-ricardo
Version: 0.1.1
Summary: Springlabs Projects Django Standard(NO ES COPIA)
Home-page: https://springlabs.ai/
Author: Ricardo Romero
Author-email: crrg1022@gmail.com
License: UNKNOWN
Project-URL: Source Code, https://gitlab.com/AlejandroBarcenas/springlabs-django-cli
Platform: UNKNOWN
Classifier: Programming Language :: Python :: 3
Classifier: License :: OSI Approved :: MIT License
Classifier: Operating System :: OS Independent
Requires-Python: >=3.6
Requires-Dist: click (==7.1.2)
Requires-Dist: requests (==2.24.0)
